{
    "$schema": "https://unpkg.com/@progress/kendo-theme-tasks@1.14.0/lib/schemas/kendo-swatch.json",
    "name": "Default Nordic",
    "product": "kendo",
    "base": "@progress/kendo-theme-default",
    "version": "5.1.2-dev.7",
    "previewColors": [
        "#ffffff",
        "#50686e",
        "#01a8c1",
        "#006989",
        "#e7607b"
    ],
    "components": [],
    "groups": [
        {
            "name": "New theme colors",
            "colorsMap": {
                "app-surface": {
                    "name": "App Surface",
                    "type": "color",
                    "value": "#ffffff"
                },
                "on-app-surface": {
                    "name": "On App Surface",
                    "type": "color",
                    "value": "#292b2c"
                },
                "subtle": {
                    "name": "Subtle",
                    "type": "color",
                    "value": "#8f9ea2"
                },
                "surface": {
                    "name": "Surface",
                    "type": "color",
                    "value": "#f8f9fa"
                },
                "surface-alt": {
                    "name": "Surface Alt",
                    "type": "color",
                    "value": "#ffffff"
                },
                "base-subtle": {
                    "name": "Base Subtle",
                    "type": "color",
                    "value": "#cddce0"
                },
                "base-subtle-hover": {
                    "name": "Base Subtle Hover",
                    "type": "color",
                    "value": "#c5d3d6"
                },
                "base-subtle-active": {
                    "name": "Base Subtle Active",
                    "type": "color",
                    "value": "#bac7cb"
                },
                "base": {
                    "name": "Base",
                    "type": "color",
                    "value": "#d6e5e9"
                },
                "base-hover": {
                    "name": "Base Hover",
                    "type": "color",
                    "value": "#cddce0"
                },
                "base-active": {
                    "name": "Base Active",
                    "type": "color",
                    "value": "#bccacd"
                },
                "base-emphasis": {
                    "name": "Base Emphasis",
                    "type": "color",
                    "value": "#a9b5b8"
                },
                "base-on-subtle": {
                    "name": "Base On Subtle",
                    "type": "color",
                    "value": "#212529"
                },
                "on-base": {
                    "name": "On Base",
                    "type": "color",
                    "value": "#212529"
                },
                "base-on-surface": {
                    "name": "Base On Surface",
                    "type": "color",
                    "value": "#212529"
                },
                "primary-subtle": {
                    "name": "Primary Subtle",
                    "type": "color",
                    "value": "#d0e3ee"
                },
                "primary-subtle-hover": {
                    "name": "Primary Subtle Hover",
                    "type": "color",
                    "value": "#B8D5E6"
                },
                "primary-subtle-active": {
                    "name": "Primary Subtle Active",
                    "type": "color",
                    "value": "#A0C7DE"
                },
                "primary": {
                    "name": "Primary",
                    "type": "color",
                    "value": "#e7607b"
                },
                "primary-hover": {
                    "name": "Primary Hover",
                    "type": "color",
                    "value": "#DA2146"
                },
                "primary-active": {
                    "name": "Primary Active",
                    "type": "color",
                    "value": "#B11B39"
                },
                "primary-emphasis": {
                    "name": "Primary Emphasis",
                    "type": "color",
                    "value": "#EF95A7"
                },
                "primary-on-subtle": {
                    "name": "Primary On Subtle",
                    "type": "color",
                    "value": "#072E45"
                },
                "on-primary": {
                    "name": "On Primary",
                    "type": "color",
                    "value": "white"
                },
                "primary-on-surface": {
                    "name": "Primary On Surface",
                    "type": "color",
                    "value": "#1274AC"
                },
                "secondary-subtle": {
                    "name": "Secondary Subtle",
                    "type": "color",
                    "value": "#f7fafb"
                },
                "secondary-subtle-hover": {
                    "name": "Secondary Subtle Hover",
                    "type": "color",
                    "value": "#f1f6f7"
                },
                "secondary-subtle-active": {
                    "name": "Secondary Subtle Active",
                    "type": "color",
                    "value": "#ebf2f4"
                },
                "secondary": {
                    "name": "Secondary",
                    "type": "color",
                    "value": "#d6e5e9"
                },
                "secondary-hover": {
                    "name": "Secondary Hover",
                    "type": "color",
                    "value": "#cddce0"
                },
                "secondary-active": {
                    "name": "Secondary Active",
                    "type": "color",
                    "value": "#bccacd"
                },
                "secondary-emphasis": {
                    "name": "Secondary Emphasis",
                    "type": "color",
                    "value": "#e0ecef"
                },
                "secondary-on-subtle": {
                    "name": "Secondary On Subtle",
                    "type": "color",
                    "value": "#4b5052"
                },
                "on-secondary": {
                    "name": "On Secondary",
                    "type": "color",
                    "value": "black"
                },
                "secondary-on-surface": {
                    "name": "Secondary On Surface",
                    "type": "color",
                    "value": "#a1acaf"
                },
                "info-subtle": {
                    "name": "Info Subtle",
                    "type": "color",
                    "value": "#cceef3"
                },
                "info-subtle-hover": {
                    "name": "Info Subtle Hover",
                    "type": "color",
                    "value": "#a6e1e9"
                },
                "info-subtle-active": {
                    "name": "Info Subtle Active",
                    "type": "color",
                    "value": "#80d4e0"
                },
                "info": {
                    "name": "Info",
                    "type": "color",
                    "value": "#01a8c1"
                },
                "info-hover": {
                    "name": "Info Hover",
                    "type": "color",
                    "value": "#01a1b9"
                },
                "info-active": {
                    "name": "Info Active",
                    "type": "color",
                    "value": "#0194aa"
                },
                "info-emphasis": {
                    "name": "Info Emphasis",
                    "type": "color",
                    "value": "#41bed1"
                },
                "info-on-subtle": {
                    "name": "Info On Subtle",
                    "type": "color",
                    "value": "#003b44"
                },
                "on-info": {
                    "name": "On Info",
                    "type": "color",
                    "value": "white"
                },
                "info-on-surface": {
                    "name": "Info On Surface",
                    "type": "color",
                    "value": "#017e91"
                },
                "success-subtle": {
                    "name": "Success Subtle",
                    "type": "color",
                    "value": "#e9f2dc"
                },
                "success-subtle-hover": {
                    "name": "Success Subtle Hover",
                    "type": "color",
                    "value": "#d8e9c1"
                },
                "success-subtle-active": {
                    "name": "Success Subtle Active",
                    "type": "color",
                    "value": "#c8dfa7"
                },
                "success": {
                    "name": "Success",
                    "type": "color",
                    "value": "#90bf4f"
                },
                "success-hover": {
                    "name": "Success Hover",
                    "type": "color",
                    "value": "#8ab74c"
                },
                "success-active": {
                    "name": "Success Active",
                    "type": "color",
                    "value": "#7fa846"
                },
                "success-emphasis": {
                    "name": "Success Emphasis",
                    "type": "color",
                    "value": "#accf7b"
                },
                "success-on-subtle": {
                    "name": "Success On Subtle",
                    "type": "color",
                    "value": "#32431c"
                },
                "on-success": {
                    "name": "On Success",
                    "type": "color",
                    "value": "white"
                },
                "success-on-surface": {
                    "name": "Success On Surface",
                    "type": "color",
                    "value": "#6c8f3b"
                },
                "warning-subtle": {
                    "name": "Warning Subtle",
                    "type": "color",
                    "value": "#fff4dd"
                },
                "warning-subtle-hover": {
                    "name": "Warning Subtle Hover",
                    "type": "color",
                    "value": "#ffecc4"
                },
                "warning-subtle-active": {
                    "name": "Warning Subtle Active",
                    "type": "color",
                    "value": "#ffe4ab"
                },
                "warning": {
                    "name": "Warning",
                    "type": "color",
                    "value": "#ffc857"
                },
                "warning-hover": {
                    "name": "Warning Hover",
                    "type": "color",
                    "value": "#f5c054"
                },
                "warning-active": {
                    "name": "Warning Active",
                    "type": "color",
                    "value": "#e0b04d"
                },
                "warning-emphasis": {
                    "name": "Warning Emphasis",
                    "type": "color",
                    "value": "#ffd681"
                },
                "warning-on-subtle": {
                    "name": "Warning On Subtle",
                    "type": "color",
                    "value": "#59461e"
                },
                "on-warning": {
                    "name": "On Warning",
                    "type": "color",
                    "value": "black"
                },
                "warning-on-surface": {
                    "name": "Warning On Surface",
                    "type": "color",
                    "value": "#bf9641"
                },
                "error-subtle": {
                    "name": "Error Subtle",
                    "type": "color",
                    "value": "#f6cfd7"
                },
                "error-subtle-hover": {
                    "name": "Error Subtle Hover",
                    "type": "color",
                    "value": "#f0abb9"
                },
                "error-subtle-active": {
                    "name": "Error Subtle Active",
                    "type": "color",
                    "value": "#e9889c"
                },
                "error": {
                    "name": "Error",
                    "type": "color",
                    "value": "#d31038"
                },
                "error-hover": {
                    "name": "Error Hover",
                    "type": "color",
                    "value": "#cb0f36"
                },
                "error-active": {
                    "name": "Error Active",
                    "type": "color",
                    "value": "#ba0e31"
                },
                "error-emphasis": {
                    "name": "Error Emphasis",
                    "type": "color",
                    "value": "#de4c6a"
                },
                "error-on-subtle": {
                    "name": "Error On Subtle",
                    "type": "color",
                    "value": "#4a0614"
                },
                "on-error": {
                    "name": "On Error",
                    "type": "color",
                    "value": "white"
                },
                "error-on-surface": {
                    "name": "Error On Surface",
                    "type": "color",
                    "value": "#9e0c2a"
                },
                "series-a": {
                    "name": "Series A",
                    "type": "color",
                    "value": "#e7607b"
                },
                "series-a-bold": {
                    "name": "Series A Bold",
                    "type": "color",
                    "value": "#ad485c"
                },
                "series-a-bolder": {
                    "name": "Series A Bolder",
                    "type": "color",
                    "value": "#74303e"
                },
                "series-a-subtle": {
                    "name": "Series A Subtle",
                    "type": "color",
                    "value": "#ed889c"
                },
                "series-a-subtler": {
                    "name": "Series A Subtler",
                    "type": "color",
                    "value": "#f3b0bd"
                },
                "series-b": {
                    "name": "Series B",
                    "type": "color",
                    "value": "#bb334f"
                },
                "series-b-bold": {
                    "name": "Series B Bold",
                    "type": "color",
                    "value": "#8c263b"
                },
                "series-b-bolder": {
                    "name": "Series B Bolder",
                    "type": "color",
                    "value": "#5e1a28"
                },
                "series-b-subtle": {
                    "name": "Series B Subtle",
                    "type": "color",
                    "value": "#cc667b"
                },
                "series-b-subtler": {
                    "name": "Series B Subtler",
                    "type": "color",
                    "value": "#dd99a7"
                },
                "series-c": {
                    "name": "Series C",
                    "type": "color",
                    "value": "#6bd2e2"
                },
                "series-c-bold": {
                    "name": "Series C Bold",
                    "type": "color",
                    "value": "#509eaa"
                },
                "series-c-bolder": {
                    "name": "Series C Bolder",
                    "type": "color",
                    "value": "#366971"
                },
                "series-c-subtle": {
                    "name": "Series C Subtle",
                    "type": "color",
                    "value": "#90dde9"
                },
                "series-c-subtler": {
                    "name": "Series C Subtler",
                    "type": "color",
                    "value": "#b5e9f1"
                },
                "series-d": {
                    "name": "Series D",
                    "type": "color",
                    "value": "#01A8C1"
                },
                "series-d-bold": {
                    "name": "Series D Bold",
                    "type": "color",
                    "value": "#017e91"
                },
                "series-d-bolder": {
                    "name": "Series D Bolder",
                    "type": "color",
                    "value": "#015461"
                },
                "series-d-subtle": {
                    "name": "Series D Subtle",
                    "type": "color",
                    "value": "#41bed1"
                },
                "series-d-subtler": {
                    "name": "Series D Subtler",
                    "type": "color",
                    "value": "#80d4e0"
                },
                "series-e": {
                    "name": "Series E",
                    "type": "color",
                    "value": "#ddc981"
                },
                "series-e-bold": {
                    "name": "Series E Bold",
                    "type": "color",
                    "value": "#a69761"
                },
                "series-e-bolder": {
                    "name": "Series E Bolder",
                    "type": "color",
                    "value": "#6f6541"
                },
                "series-e-subtle": {
                    "name": "Series E Subtle",
                    "type": "color",
                    "value": "#e6d7a1"
                },
                "series-e-subtler": {
                    "name": "Series E Subtler",
                    "type": "color",
                    "value": "#eee4c0"
                },
                "series-f": {
                    "name": "Series F",
                    "type": "color",
                    "value": "#c09e2f"
                },
                "series-f-bold": {
                    "name": "Series F Bold",
                    "type": "color",
                    "value": "#907723"
                },
                "series-f-bolder": {
                    "name": "Series F Bolder",
                    "type": "color",
                    "value": "#604f18"
                },
                "series-f-subtle": {
                    "name": "Series F Subtle",
                    "type": "color",
                    "value": "#d0b663"
                },
                "series-f-subtler": {
                    "name": "Series F Subtler",
                    "type": "color",
                    "value": "#e0cf97"
                }
            }
        }
    ]
}
